README.md
setup.cfg
setup.py
nexus_api_python_client/__init__.py
nexus_api_python_client/api_client.py
nexus_api_python_client/configuration.py
nexus_api_python_client/exceptions.py
nexus_api_python_client/rest.py
nexus_api_python_client.egg-info/PKG-INFO
nexus_api_python_client.egg-info/SOURCES.txt
nexus_api_python_client.egg-info/dependency_links.txt
nexus_api_python_client.egg-info/requires.txt
nexus_api_python_client.egg-info/top_level.txt
nexus_api_python_client/api/__init__.py
nexus_api_python_client/api/assets_api.py
nexus_api_python_client/api/blob_store_api.py
nexus_api_python_client/api/components_api.py
nexus_api_python_client/api/content_selectors_api.py
nexus_api_python_client/api/email_api.py
nexus_api_python_client/api/formats_api.py
nexus_api_python_client/api/lifecycle_api.py
nexus_api_python_client/api/manage_iq_server_configuration_api.py
nexus_api_python_client/api/product_licensing_api.py
nexus_api_python_client/api/read_only_api.py
nexus_api_python_client/api/repositories_api.py
nexus_api_python_client/api/repository_management_api.py
nexus_api_python_client/api/routing_rules_api.py
nexus_api_python_client/api/script_api.py
nexus_api_python_client/api/search_api.py
nexus_api_python_client/api/security_certificates_api.py
nexus_api_python_client/api/security_management_api.py
nexus_api_python_client/api/security_management_ldap_api.py
nexus_api_python_client/api/security_management_privileges_api.py
nexus_api_python_client/api/security_management_realms_api.py
nexus_api_python_client/api/security_management_roles_api.py
nexus_api_python_client/api/security_management_users_api.py
nexus_api_python_client/api/status_api.py
nexus_api_python_client/api/support_api.py
nexus_api_python_client/api/tasks_api.py
nexus_api_python_client/models/__init__.py
nexus_api_python_client/models/abstract_api_repository.py
nexus_api_python_client/models/api_certificate.py
nexus_api_python_client/models/api_create_user.py
nexus_api_python_client/models/api_email_configuration.py
nexus_api_python_client/models/api_email_validation.py
nexus_api_python_client/models/api_license_details_xo.py
nexus_api_python_client/models/api_privilege.py
