Metadata-Version: 1.0
Name: nexus-api-python-client
Version: 1.0.3
Summary: Nexus Repository Manager Python API Client
Home-page: UNKNOWN
Author: Simone Bruzzechesse
Author-email: b.sim619@gmail.com
License: UNKNOWN
Keywords: Nexus API,Python,Nexus Repository Manager REST API
Platform: UNKNOWN
